tokenlay/__init__.py
tokenlay-0.0.1.dist-info/licenses/LICENSE
tokenlay-0.0.1.dist-info/METADATA
tokenlay-0.0.1.dist-info/WHEEL
tokenlay-0.0.1.dist-info/top_level.txt
tokenlay-0.0.1.dist-info/RECORD
