Metadata-Version: 2.4
Name: tokenlay
Version: 0.0.1
Summary: Python SDK for Tokenlay API (placeholder)
Author-email: Tokenlay <hello@tokenlay.com>
License: MIT License
Project-URL: Homepage, https://tokenlay.com
Project-URL: Repository, https://github.com/tokenlay/tokenlay-sdk-py
Classifier: Development Status :: 1 - Planning
Classifier: Intended Audience :: Developers
Classifier: License :: OSI Approved :: MIT License
Classifier: Programming Language :: Python :: 3
Classifier: Programming Language :: Python :: 3.8
Classifier: Programming Language :: Python :: 3.9
Classifier: Programming Language :: Python :: 3.10
Classifier: Programming Language :: Python :: 3.11
Classifier: Programming Language :: Python :: 3.12
Requires-Python: >=3.8
License-File: LICENSE
Dynamic: license-file
